easy-install.pth
site.py
__pycache__/site.cpython-36.pyc
jgtextrank-0.1.4-py3.6.egg/EGG-INFO/SOURCES.txt
jgtextrank-0.1.4-py3.6.egg/EGG-INFO/not-zip-safe
jgtextrank-0.1.4-py3.6.egg/jgtextrank/__init__.py
jgtextrank-0.1.4-py3.6.egg/jgtextrank/core.py
jgtextrank-0.1.4-py3.6.egg/jgtextrank/decorators.py
jgtextrank-0.1.4-py3.6.egg/jgtextrank/exceptions.py
jgtextrank-0.1.4-py3.6.egg/jgtextrank/metrics.py
jgtextrank-0.1.4-py3.6.egg/jgtextrank/utility.py
jgtextrank-0.1.4-py3.6.egg/jgtextrank/__pycache__/__init__.cpython-36.pyc
jgtextrank-0.1.4-py3.6.egg/jgtextrank/__pycache__/core.cpython-36.pyc
jgtextrank-0.1.4-py3.6.egg/jgtextrank/__pycache__/decorators.cpython-36.pyc
jgtextrank-0.1.4-py3.6.egg/jgtextrank/__pycache__/exceptions.cpython-36.pyc
jgtextrank-0.1.4-py3.6.egg/jgtextrank/__pycache__/metrics.cpython-36.pyc
jgtextrank-0.1.4-py3.6.egg/jgtextrank/__pycache__/utility.cpython-36.pyc
jgtextrank-0.1.4-py3.6.egg/jgtextrank/jgtextrank.egg-info/PKG-INFO
jgtextrank-0.1.4-py3.6.egg/jgtextrank/jgtextrank.egg-info/SOURCES.txt
jgtextrank-0.1.4-py3.6.egg/jgtextrank/jgtextrank.egg-info/dependency_links.txt
jgtextrank-0.1.4-py3.6.egg/jgtextrank/jgtextrank.egg-info/not-zip-safe
jgtextrank-0.1.4-py3.6.egg/jgtextrank/jgtextrank.egg-info/requires.txt
jgtextrank-0.1.4-py3.6.egg/jgtextrank/jgtextrank.egg-info/top_level.txt
jgtextrank-0.1.4-py3.6.egg/jgtextrank/preprocessing/__init__.py
jgtextrank-0.1.4-py3.6.egg/jgtextrank/preprocessing/normaliser.py
jgtextrank-0.1.4-py3.6.egg/jgtextrank/preprocessing/segmentation.py
jgtextrank-0.1.4-py3.6.egg/jgtextrank/preprocessing/__pycache__/__init__.cpython-36.pyc
jgtextrank-0.1.4-py3.6.egg/jgtextrank/preprocessing/__pycache__/normaliser.cpython-36.pyc
jgtextrank-0.1.4-py3.6.egg/jgtextrank/preprocessing/__pycache__/segmentation.cpython-36.pyc
jgtextrank-0.1.4-py3.6.egg/jgtextrank.egg-info/PKG-INFO
jgtextrank-0.1.4-py3.6.egg/jgtextrank.egg-info/SOURCES.txt
jgtextrank-0.1.4-py3.6.egg/jgtextrank.egg-info/dependency_links.txt
jgtextrank-0.1.4-py3.6.egg/jgtextrank.egg-info/not-zip-safe
jgtextrank-0.1.4-py3.6.egg/jgtextrank.egg-info/requires.txt
jgtextrank-0.1.4-py3.6.egg/jgtextrank.egg-info/top_level.txt
jgtextrank-0.1.4.dist-info/DESCRIPTION.rst
jgtextrank-0.1.4.dist-info/LICENSE.txt
jgtextrank-0.1.4.dist-info/METADATA
jgtextrank-0.1.4.dist-info/RECORD
jgtextrank-0.1.4.dist-info/WHEEL
jgtextrank-0.1.4.dist-info/metadata.json
jgtextrank-0.1.4.dist-info/top_level.txt
