Metadata-Version: 2.0
Name: jgtextrank
Version: 0.1.4
Summary: Yet another Python implementation of TextRank: package for the creation, manipulation, and study of TextRank algorithm based keywords extraction and summarisation
Home-page: https://github.com/jerrygaoLondon/jgtextrank
Author: Jie Gao
Author-email: j.gao@sheffield.ac.uk
License: MIT
Keywords: textrank,parsing,natural language processing,nlp,keywords extraction,term extraction,text summarisation,text analytics,text mining,feature extraction,machine learning,graph algorithm,computational linguistics
Platform: UNKNOWN
Classifier: Development Status :: 4 - Beta
Classifier: Intended Audience :: Developers
Classifier: Intended Audience :: Education
Classifier: Intended Audience :: Information Technology
Classifier: Intended Audience :: Science/Research
Classifier: License :: OSI Approved :: MIT License
Classifier: Operating System :: OS Independent
Classifier: Programming Language :: Python :: 3 :: Only
Classifier: Topic :: Scientific/Engineering :: Artificial Intelligence
Classifier: Topic :: Scientific/Engineering :: Human Machine Interfaces
Classifier: Topic :: Scientific/Engineering :: Information Analysis
Classifier: Topic :: Text Processing :: General
Classifier: Topic :: Text Processing :: Indexing
Classifier: Topic :: Text Processing :: Linguistic
Classifier: Topic :: Text Processing :: Filters
Classifier: Topic :: Text Processing :: Linguistic
Provides-Extra: dev
Provides-Extra: test
Requires-Dist: nltk
Requires-Dist: networkx
Provides-Extra: dev
Requires-Dist: check-manifest; extra == 'dev'
Requires-Dist: matplotlib; extra == 'dev'
Provides-Extra: test
Requires-Dist: coverage; extra == 'test'
Requires-Dist: matplotlib; extra == 'test'
Requires-Dist: scipy; extra == 'test'
